{"nirvanaTracksByIn":[{"Id":5,"Name":"Smells Like Teen Spirit","ArtistId":3,"Album":"Nevermind","Year":1991},{"Id":6,"Name":"Heart-Shaped Box","ArtistId":3,"Album":"In Utero","Year":1993}],"pearlJam":{"Id":4,"Name":"Pearl Jam"},"faithNoMore":{"Id":1,"Name":"Faith No More"},"latestTracks":[{"Id":2,"Name":"Ashes to Ashes","ArtistId":1,"Album":"Album of the Year","Year":1997},{"Id":4,"Name":"Lakini's Juice","ArtistId":2,"Album":"Secret Samadhi","Year":1997}],"heartShapedBox":{"Id":6,"Name":"Heart-Shaped Box","ArtistId":3,"Album":"In Utero","Year":1993}}